deck_chores/__init__.py
deck_chores/config.py
deck_chores/indexes.py
deck_chores/jobs.py
deck_chores/main.py
deck_chores/parsers.py
deck_chores/utils.py
deck_chores-1.4.10.dist-info/LICENSE.txt
deck_chores-1.4.10.dist-info/METADATA
deck_chores-1.4.10.dist-info/WHEEL
deck_chores-1.4.10.dist-info/entry_points.txt
deck_chores-1.4.10.dist-info/RECORD
