Metadata-Version: 2.1
Name: deck-chores
Version: 1.4.10
Summary: Job scheduler for Docker containers, configured via container labels.
Home-page: https://github.com/funkyfuture/deck-chores
License: ISC
Keywords: docker,cron,scheduler,jobs,labels,metadata
Author: Frank Sachsenheim
Author-email: funkyfuture@riseup.net
Requires-Python: >=3.12,<4.0
Classifier: Development Status :: 5 - Production/Stable
Classifier: Intended Audience :: System Administrators
Classifier: License :: OSI Approved
Classifier: License :: OSI Approved :: ISC License (ISCL)
Classifier: Natural Language :: English
Classifier: Programming Language :: Python :: 3
Classifier: Programming Language :: Python :: 3.12
Classifier: Programming Language :: Python :: Implementation :: CPython
Requires-Dist: apscheduler (>=3.6,<4.0)
Requires-Dist: cerberus (>=1.3.4,<2.0.0)
Requires-Dist: docker[ssh] (>=7,<8)
Requires-Dist: fasteners (>=0.14,<0.15)
Requires-Dist: python-dateutil (>=2.8.1,<3.0.0)
Requires-Dist: pytz
Project-URL: Documentation, https://deck-chores.readthedocs.org/
Project-URL: Repository, https://github.com/funkyfuture/deck-chores
